wexample_pseudocode-0.0.69.dist-info/METADATA
wexample_pseudocode-0.0.69.dist-info/WHEEL
wexample_pseudocode-0.0.69.dist-info/entry_points.txt
wexample_pseudocode/__init__.py
wexample_pseudocode/common/__init__.py
wexample_pseudocode/common/docstring.py
wexample_pseudocode/common/type_normalizer.py
wexample_pseudocode/common/with_config_registry.py
wexample_pseudocode/config/__init__.py
wexample_pseudocode/config/class_config.py
wexample_pseudocode/config/class_method_config.py
wexample_pseudocode/config/class_property_config.py
wexample_pseudocode/config/constant_config.py
wexample_pseudocode/config/doc_comment_config.py
wexample_pseudocode/config/doc_comment_parameter_config.py
wexample_pseudocode/config/doc_comment_return_config.py
wexample_pseudocode/config/function_config.py
wexample_pseudocode/config/function_parameter_config.py
wexample_pseudocode/config/generator_config.py
wexample_pseudocode/config/method_parameter_config.py
wexample_pseudocode/generator/__init__.py
wexample_pseudocode/generator/abstract_generator.py
wexample_pseudocode/generator/code_generator.py
wexample_pseudocode/generator/pseudocode_generator.py
wexample_pseudocode/parser/__init__.py
wexample_pseudocode/parser/class_parser.py
wexample_pseudocode/parser/function_parser.py
wexample_pseudocode/parser/module_parser.py
wexample_pseudocode/py.typed
wexample_pseudocode-0.0.69.dist-info/RECORD
